LICENSE
MANIFEST.in
Makefile
README.rst
requirements.txt
setup.py
mpltools/__init__.py
mpltools/_config.py
mpltools/animation.py
mpltools/color.py
mpltools/layout.py
mpltools/mpltoolsrc
mpltools/util.py
mpltools.egg-info/PKG-INFO
mpltools.egg-info/SOURCES.txt
mpltools.egg-info/dependency_links.txt
mpltools.egg-info/top_level.txt
mpltools/annotation/__init__.py
mpltools/annotation/_slopemarker.py
mpltools/io/__init__.py
mpltools/io/core.py
mpltools/special/__init__.py
mpltools/special/errorfill.py
mpltools/special/hinton.py
mpltools/sphinx/__init__.py
mpltools/sphinx/plot2rst.py
mpltools/style/__init__.py
mpltools/style/core.py
mpltools/style/dark_background.rc
mpltools/style/ggplot.rc
mpltools/style/grayscale.rc
mpltools/style/ieee.transaction.fullpage.rc
mpltools/style/ieee.transaction.rc
mpltools/style/jfm.rc
mpltools/style/langmuir.fullpage.rc
mpltools/style/langmuir.rc
mpltools/style/pof.rc
mpltools/widgets/__init__.py
mpltools/widgets/rectangle_selector.py
mpltools/widgets/slider.py