Metadata-Version: 1.0
Name: mpltools
Version: 0.1
Summary: Tools for Matplotlib
Home-page: http://tonysyu.github.com/mpltools/
Author: Tony S. Yu
Author-email: tsyu80@gmail.com
License: Modified BSD
Download-URL: http://github.com/tonysyu/mpltools
Platform: UNKNOWN
